{
  "name": "albumarchitect",
  "version-semver": "0.1.0",
  "dependencies": [
    {
      "name": "abseil",
      "version>=": "20240722.0"
    },
    {
      "name": "fmt",
      "version>=": "11.0.2"
    },
    {
      "name": "spdlog",
      "version>=": "1.14.1"
    },
    {
      "name": "boost-core",
      "version>=": "1.83.0"
    },
    {
      "name": "boost-graph",
      "version>=": "1.83.0"
    },
    {
      "name": "boost-serialization",
      "version>=": "1.83.0"
    },
    {
      "name": "boost-filesystem",
      "version>=": "1.83.0"
    },
    {
      "name": "hash-library",
      "version>=": "8#3"
    },
    {
      "name": "magic-enum",
      "version>=": "0.9.6#1"
    },
    {
      "name": "opencv",
      "version>=": "4.8.0#1",
      "features": [
        "contrib"
      ]
    },
    {
      "name": "openimageio",
      "version>=": "2.5.14.0",
      "features": [
        "opencv",
        "gif",
        "libheif"
      ]
    },
    {
      "name": "tbb",
      "version>=": "2021.13.0"
    }
  ],
  "default-features": [],
  "features": {
    "test": {
      "description": "Dependencies for testing",
      "dependencies": [
        {
          "name": "catch2",
          "version>=": "3.7.1"
        }
      ]
    }
  },
  "builtin-baseline": "dd3adcf020e69077e83e92a0a293ceca734f6288"
}
